UTRme/__init__.py
UTRme/__main__.py
UTRme/utrme.py
UTRme-1.1.0.dist-info/METADATA
UTRme-1.1.0.dist-info/RECORD
UTRme-1.1.0.dist-info/WHEEL
UTRme-1.1.0.dist-info/entry_points.txt
UTRme-1.1.0.dist-info/top_level.txt
