Metadata-Version: 2.1
Name: UTRme
Version: 1.1.0
Summary: UTRme
Home-page: UNKNOWN
Author: Santiago Radío
Author-email: sradio91@gmail.com
License: MIT
Keywords: utrme,splice-leader,polyA,UTR,trans-splicing
Platform: UNKNOWN
Classifier: Development Status :: 5 - Production/Stable
Classifier: Environment :: Console
Classifier: Intended Audience :: Science/Research
Classifier: License :: OSI Approved :: MIT License
Classifier: Operating System :: Unix
Classifier: Natural Language :: English
Classifier: Programming Language :: Python :: 3
Classifier: Topic :: Scientific/Engineering :: Bio-Informatics
Requires-Dist: numpy
Requires-Dist: xlsxwriter
Requires-Dist: scipy
Requires-Dist: python-levenshtein
Requires-Dist: fuzzywuzzy
Requires-Dist: regex
Requires-Dist: pyfaidx
Requires-Dist: pysam
Requires-Dist: pandas
Requires-Dist: BioPython
Requires-Dist: argparse
Requires-Dist: twine
Requires-Dist: matplotlib
Requires-Dist: seaborn
